LICENSE
MANIFEST.in
README.md
setup.cfg
setup.py
qme/__init__.py
qme/defaults.py
qme/exceptions.py
qme/version.py
qme.egg-info/PKG-INFO
qme.egg-info/SOURCES.txt
qme.egg-info/dependency_links.txt
qme.egg-info/entry_points.txt
qme.egg-info/not-zip-safe
qme.egg-info/requires.txt
qme.egg-info/top_level.txt
qme/app/__init__.py
qme/app/api.py
qme/app/config.py
qme/app/server.py
qme/app/static/css/style.css
qme/app/static/js/home.js
qme/app/templates/base.html
qme/app/templates/executors/shell.html
qme/app/templates/home/filesystem-index.html
qme/app/templates/home/index.html
qme/app/templates/home/relational-index.html
qme/app/views/__init__.py
qme/app/views/executors.py
qme/app/views/main.py
qme/client/__init__.py
qme/client/actions.py
qme/client/clear.py
qme/client/config.py
qme/client/generate.py
qme/client/get.py
qme/client/listing.py
qme/client/run.py
qme/client/search.py
qme/client/start.py
qme/logger/__init__.py
qme/logger/message.py
qme/logger/namer.py
qme/logger/progress.py
qme/logger/spinner.py
qme/main/__init__.py
qme/main/config/__init__.py
qme/main/config/config.ini
qme/main/database/__init__.py
qme/main/database/base.py
qme/main/database/filesystem.py
qme/main/database/models.py
qme/main/database/relational.py
qme/main/database/sqlite.py
qme/main/executor/__init__.py
qme/main/executor/base.py
qme/main/executor/shell.py
qme/main/executor/slurm.py
qme/utils/__init__.py
qme/utils/command.py
qme/utils/file.py
qme/utils/prompt.py
qme/utils/regex.py
tests/__init__.py
tests/test_executor_shell.py
tests/test_executor_slurm.py
tests/test_filesystem.py
tests/test_relational.py